<?xml version="1.0" encoding="UTF-8" standalone="no"?>
<ocrresult>
<docinfo dpix="300" dpiy="300" height="3300" href="C:\Tomcat6.0\apache-tomcat-6.0.16\webapps\OCRTools\png\1256545321178.png" width="2552"/>
<words>
<word bottom="105" left="1195" right="1231" top="130">

73
</word>
<word bottom="2951" left="308" right="373" top="2977">

1989
</word>
<word bottom="2949" left="607" right="672" top="2975">

1988
</word>
<word bottom="2947" left="907" right="974" top="2972">

1987
</word>
<word bottom="2944" left="1207" right="1271" top="2969">

1986
</word>
<word bottom="2942" left="1507" right="1571" top="2967">

1985
</word>
<word bottom="2940" left="1805" right="1870" top="2965">

1984
</word>
<word bottom="2937" left="2106" right="2169" top="2962">

1983
</word>
<word bottom="2799" left="273" right="410" top="2834">

$13,850
</word>
<word bottom="2798" left="572" right="708" top="2832">

$13,082
</word>
<word bottom="2795" left="871" right="1008" top="2829">

$11,813
</word>
<word bottom="2793" left="1171" right="1308" top="2827">

$11,496
</word>
<word bottom="2790" left="1470" right="1607" top="2824">

$11,018
</word>
<word bottom="2787" left="1781" right="1912" top="2823">

$10,408
</word>
<word bottom="2784" left="2069" right="2206" top="2819">

$10,036
</word>
<word bottom="2764" left="348" right="408" top="2792">

449
</word>
<word bottom="2762" left="650" right="708" top="2790">

339
</word>
<word bottom="2759" left="947" right="1007" top="2787">

279
</word>
<word bottom="2757" left="1248" right="1305" top="2784">

201
</word>
<word bottom="2755" left="1549" right="1605" top="2783">

185
</word>
<word bottom="2752" left="1846" right="1906" top="2779">

276
</word>
<word bottom="2749" left="2145" right="2204" top="2777">

252
</word>
<word bottom="2701" left="300" right="409" top="2735">

14,299
</word>
<word bottom="2698" left="599" right="706" top="2733">

13,421
</word>
<word bottom="2697" left="898" right="1007" top="2730">

12,092
</word>
<word bottom="2694" left="1198" right="1308" top="2728">

11,697
</word>
<word bottom="2691" left="1498" right="1606" top="2725">

11,203
</word>
<word bottom="2689" left="1797" right="1907" top="2723">

10,684
</word>
<word bottom="2688" left="2096" right="2205" top="2720">

10,288
</word>
<word bottom="2644" left="299" right="408" top="2678">

12,559
</word>
<word bottom="2642" left="598" right="707" top="2676">

12,252
</word>
<word bottom="2638" left="897" right="1008" top="2673">

11,186
</word>
<word bottom="2637" left="1197" right="1306" top="2670">

10,300
</word>
<word bottom="2634" left="1497" right="1607" top="2668">

10,187
</word>
<word bottom="2632" left="1813" right="1903" top="2666">

9,501
</word>
<word bottom="2629" left="2113" right="2205" top="2663">

9,257
</word>
<word bottom="2609" left="348" right="409" top="2636">

474
</word>
<word bottom="2607" left="648" right="708" top="2635">

490
</word>
<word bottom="2605" left="947" right="1008" top="2632">

420
</word>
<word bottom="2602" left="1246" right="1305" top="2629">

408
</word>
<word bottom="2600" left="1548" right="1605" top="2627">

323
</word>
<word bottom="2597" left="1847" right="1903" top="2624">

315
</word>
<word bottom="2594" left="2147" right="2204" top="2621">

306
</word>
<word bottom="2577" left="372" right="409" top="2581">

-
</word>
<word bottom="2566" left="650" right="706" top="2594">

102
</word>
<word bottom="2573" left="971" right="1008" top="2576">

-
</word>
<word bottom="2570" left="1270" right="1307" top="2573">

-
</word>
<word bottom="2568" left="1569" right="1607" top="2571">

-
</word>
<word bottom="2565" left="1869" right="1906" top="2569">

-
</word>
<word bottom="2563" left="2168" right="2205" top="2566">

-
</word>
<word bottom="2505" left="298" right="407" top="2540">

13,033
</word>
<word bottom="2502" left="598" right="708" top="2537">

12,844
</word>
<word bottom="2500" left="897" right="1007" top="2535">

11,606
</word>
<word bottom="2498" left="1196" right="1305" top="2532">

10,708
</word>
<word bottom="2495" left="1496" right="1606" top="2529">

10,510
</word>
<word bottom="2493" left="1813" right="1905" top="2527">

9,816
</word>
<word bottom="2491" left="2113" right="2203" top="2525">

9,563
</word>
<word bottom="2448" left="319" right="407" top="2481">

1,266
</word>
<word bottom="2451" left="648" right="707" top="2479">

577
</word>
<word bottom="2449" left="945" right="1005" top="2476">

486
</word>
<word bottom="2446" left="1244" right="1304" top="2474">

989
</word>
<word bottom="2444" left="1545" right="1604" top="2472">

693
</word>
<word bottom="2441" left="1844" right="1903" top="2469">

868
</word>
<word bottom="2439" left="2144" right="2202" top="2467">

725
</word>
<word bottom="2413" left="346" right="407" top="2441">

469
</word>
<word bottom="2411" left="648" right="703" top="2439">

501
</word>
<word bottom="2408" left="945" right="1006" top="2436">

490
</word>
<word bottom="2406" left="1247" right="1302" top="2433">

521
</word>
<word bottom="2403" left="1544" right="1604" top="2431">

498
</word>
<word bottom="2401" left="1843" right="1903" top="2428">

496
</word>
<word bottom="2398" left="2143" right="2202" top="2425">

436
</word>
<word bottom="2372" left="346" right="407" top="2400">

237
</word>
<word bottom="2370" left="667" right="705" top="2398">

82
</word>
<word bottom="2368" left="968" right="1002" top="2395">

11
</word>
<word bottom="2365" left="1244" right="1304" top="2392">

214
</word>
<word bottom="2363" left="1546" right="1604" top="2389">

126
</word>
<word bottom="2360" left="1846" right="1904" top="2388">

157
</word>
<word bottom="2357" left="2146" right="2201" top="2385">

165
</word>
<word bottom="2315" left="348" right="406" top="2343">

560
</word>
<word bottom="2305" left="675" right="720" top="2340">

(6)
</word>
<word bottom="2303" left="953" right="1019" top="2338">

(15)
</word>
<word bottom="2307" left="1244" right="1305" top="2336">

254
</word>
<word bottom="2305" left="1566" right="1604" top="2333">

69
</word>
<word bottom="2303" left="1843" right="1902" top="2331">

215
</word>
<word bottom="2300" left="2146" right="2203" top="2327">

124
</word>
<word bottom="2275" left="366" right="405" top="2301">

24
</word>
<word bottom="2273" left="645" right="703" top="2300">

828
</word>
<word bottom="2262" left="931" right="1017" top="2297">

(203)
</word>
<word bottom="2259" left="1230" right="1341" top="2295">

(293)(u
</word>
<word bottom="2257" left="1551" right="1616" top="2292">

(70)
</word>
<word bottom="2262" left="1846" right="1902" top="2289">

154
</word>
<word bottom="2260" left="2143" right="2202" top="2287">

397
</word>
<word bottom="2187" left="2165" right="2202" top="2191">

^
</word>
<word bottom="2136" left="346" right="405" top="2164">

584
</word>
<word bottom="2134" left="645" right="703" top="2162">

822
</word>
<word bottom="2124" left="931" right="1017" top="2159">

(218)
</word>
<word bottom="2121" left="1251" right="1317" top="2157">

(39)
</word>
<word bottom="2119" left="1572" right="1616" top="2154">

(1)
</word>
<word bottom="2124" left="1843" right="1902" top="2152">

369
</word>
<word bottom="2122" left="2143" right="2199" top="2150">

521
</word>
<word bottom="2096" left="368" right="403" top="2123">

18
</word>
<word bottom="2094" left="665" right="702" top="2122">

25
</word>
<word bottom="2091" left="964" right="1002" top="2118">

49
</word>
<word bottom="2088" left="1264" right="1302" top="2115">

66
</word>
<word bottom="2086" left="1563" right="1601" top="2113">

63
</word>
<word bottom="2083" left="1862" right="1898" top="2111">

61
</word>
<word bottom="2081" left="2162" right="2199" top="2108">

62
</word>
<word bottom="2036" left="267" right="283" top="2067">

$
</word>
<word bottom="2038" left="345" right="404" top="2066">

566
</word>
<word bottom="2034" left="566" right="582" top="2065">

$
</word>
<word bottom="2036" left="644" right="703" top="2063">

797
</word>
<word bottom="2031" left="865" right="882" top="2063">

$
</word>
<word bottom="2026" left="930" right="1017" top="2061">

(267)
</word>
<word bottom="2029" left="1165" right="1181" top="2060">

$
</word>
<word bottom="2023" left="1229" right="1316" top="2059">

(105)
</word>
<word bottom="2027" left="1464" right="1480" top="2057">

$
</word>
<word bottom="2020" left="1549" right="1616" top="2056">

(64)
</word>
<word bottom="2024" left="1763" right="1780" top="2055">

$
</word>
<word bottom="2026" left="1842" right="1900" top="2053">

308
</word>
<word bottom="2021" left="2063" right="2079" top="2053">

$
</word>
<word bottom="2023" left="2140" right="2200" top="2051">

459
</word>
<word bottom="1889" left="265" right="282" top="1920">

$
</word>
<word bottom="1891" left="332" right="403" top="1918">

4.27
</word>
<word bottom="1887" left="564" right="581" top="1918">

$
</word>
<word bottom="1889" left="655" right="701" top="1917">

.30
</word>
<word bottom="1885" left="863" right="880" top="1915">

$
</word>
<word bottom="1878" left="938" right="1014" top="1914">

(.43)
</word>
<word bottom="1882" left="1162" right="1179" top="1913">

$
</word>
<word bottom="1884" left="1233" right="1299" top="1911">

1.28
</word>
<word bottom="1879" left="1462" right="1478" top="1910">

$
</word>
<word bottom="1881" left="1553" right="1598" top="1909">

.05
</word>
<word bottom="1878" left="1761" right="1778" top="1908">

$
</word>
<word bottom="1879" left="1833" right="1899" top="1906">

1.09
</word>
<word bottom="1875" left="2061" right="2077" top="1905">

$
</word>
<word bottom="1876" left="2151" right="2197" top="1904">

.45
</word>
<word bottom="1841" left="639" right="715" top="1876">

(.51)
</word>
<word bottom="1845" left="2162" right="2200" top="1848">

-
</word>
<word bottom="1810" left="355" right="402" top="1837">

.19
</word>
<word bottom="1808" left="633" right="702" top="1835">

5.69
</word>
<word bottom="1798" left="918" right="1015" top="1833">

(1.38)
</word>
<word bottom="1795" left="1217" right="1340" top="1830">

(2.00)(b)
</word>
<word bottom="1796" left="1537" right="1614" top="1828">

(.48)
</word>
<word bottom="1797" left="1831" right="1898" top="1825">

1.08
</word>
<word bottom="1795" left="2128" right="2198" top="1823">

2.89
</word>
<word bottom="1669" left="263" right="279" top="1699">

$
</word>
<word bottom="1671" left="329" right="400" top="1698">

4.46
</word>
<word bottom="1667" left="562" right="578" top="1698">

$
</word>
<word bottom="1669" left="631" right="699" top="1697">

5.48
</word>
<word bottom="1665" left="861" right="878" top="1695">

$
</word>
<word bottom="1660" left="915" right="1013" top="1694">

(1.81)
</word>
<word bottom="1662" left="1161" right="1177" top="1693">

$
</word>
<word bottom="1656" left="1236" right="1312" top="1691">

(.72)
</word>
<word bottom="1660" left="1460" right="1476" top="1690">

$
</word>
<word bottom="1654" left="1535" right="1611" top="1689">

(.43)
</word>
<word bottom="1657" left="1759" right="1776" top="1688">

8
</word>
<word bottom="1660" left="1880" right="1898" top="1686">

7
</word>
<word bottom="1655" left="2058" right="2075" top="1686">

$
</word>
<word bottom="1656" left="2127" right="2197" top="1684">

3.34
</word>
<word bottom="1629" left="263" right="280" top="1660">

$
</word>
<word bottom="1631" left="309" right="400" top="1659">

26.02
</word>
<word bottom="1627" left="562" right="579" top="1658">

$
</word>
<word bottom="1629" left="609" right="699" top="1656">

24.92
</word>
<word bottom="1625" left="862" right="879" top="1655">

$
</word>
<word bottom="1626" left="908" right="1000" top="1654">

25.66
</word>
<word bottom="1622" left="1161" right="1178" top="1652">

$
</word>
<word bottom="1623" left="1209" right="1299" top="1652">

30.03
</word>
<word bottom="1619" left="1461" right="1477" top="1650">

$
</word>
<word bottom="1621" left="1509" right="1599" top="1649">

33.47
</word>
<word bottom="1617" left="1760" right="1776" top="1647">

$
</word>
<word bottom="1618" left="1807" right="1898" top="1686">

326..614
</word>
<word bottom="1614" left="2059" right="2076" top="1645">

$
</word>
<word bottom="1616" left="2107" right="2197" top="1644">

37.79
</word>
<word bottom="1548" left="262" right="278" top="1579">

$
</word>
<word bottom="1550" left="308" right="398" top="1577">

62.25
</word>
<word bottom="1545" left="561" right="578" top="1576">

$
</word>
<word bottom="1547" left="606" right="699" top="1575">

48.88
</word>
<word bottom="1543" left="860" right="878" top="1574">

$
</word>
<word bottom="1545" left="909" right="997" top="1573">

39.75
</word>
<word bottom="1540" left="1161" right="1177" top="1571">

$
</word>
<word bottom="1542" left="1208" right="1297" top="1571">

38.25
</word>
<word bottom="1538" left="1460" right="1477" top="1569">

$
</word>
<word bottom="1539" left="1508" right="1597" top="1568">

39.75
</word>
<word bottom="1535" left="1759" right="1776" top="1566">

$
</word>
<word bottom="1537" left="1807" right="1896" top="1565">

37.88
</word>
<word bottom="1533" left="2059" right="2075" top="1563">

$
</word>
<word bottom="1534" left="2104" right="2196" top="1562">

41.00
</word>
<word bottom="1509" left="262" right="279" top="1538">

$
</word>
<word bottom="1509" left="309" right="399" top="1537">

64.25
</word>
<word bottom="1505" left="562" right="578" top="1535">

$
</word>
<word bottom="1506" left="609" right="699" top="1535">

51.00
</word>
<word bottom="1502" left="861" right="877" top="1533">

$
</word>
<word bottom="1503" left="907" right="999" top="1531">

62.50
</word>
<word bottom="1499" left="1160" right="1177" top="1531">

$
</word>
<word bottom="1501" left="1206" right="1296" top="1529">

43.13
</word>
<word bottom="1499" left="1460" right="1476" top="1528">

$
</word>
<word bottom="1499" left="1505" right="1595" top="1526">

45.25
</word>
<word bottom="1495" left="1758" right="1776" top="1525">

$
</word>
<word bottom="1496" left="1804" right="1895" top="1524">

44.75
</word>
<word bottom="1494" left="2058" right="2074" top="1523">

$
</word>
<word bottom="1493" left="2104" right="2195" top="1521">

42.38
</word>
<word bottom="1466" left="261" right="278" top="1496">

$
</word>
<word bottom="1468" left="307" right="398" top="1495">

46.88
</word>
<word bottom="1464" left="560" right="577" top="1495">

$
</word>
<word bottom="1466" left="608" right="697" top="1494">

38.25
</word>
<word bottom="1461" left="860" right="876" top="1492">

$
</word>
<word bottom="1463" left="908" right="997" top="1491">

36.13
</word>
<word bottom="1459" left="1159" right="1175" top="1489">

$
</word>
<word bottom="1460" left="1207" right="1297" top="1488">

34.50
</word>
<word bottom="1456" left="1458" right="1475" top="1487">

$
</word>
<word bottom="1458" left="1506" right="1596" top="1486">

36.50
</word>
<word bottom="1454" left="1758" right="1774" top="1484">

$
</word>
<word bottom="1455" left="1805" right="1895" top="1484">

32.38
</word>
<word bottom="1452" left="2057" right="2073" top="1482">

$
</word>
<word bottom="1453" left="2105" right="2194" top="1480">

31.88
</word>
<word bottom="1425" left="262" right="278" top="1456">

$
</word>
<word bottom="1427" left="330" right="400" top="1454">

3.04
</word>
<word bottom="1423" left="561" right="577" top="1454">

$
</word>
<word bottom="1425" left="630" right="699" top="1452">

3.04
</word>
<word bottom="1420" left="861" right="877" top="1452">

$
</word>
<word bottom="1422" left="929" right="998" top="1449">

3.04
</word>
<word bottom="1418" left="1160" right="1176" top="1449">

$
</word>
<word bottom="1420" left="1228" right="1298" top="1447">

3.04
</word>
<word bottom="1416" left="1459" right="1476" top="1445">

$
</word>
<word bottom="1417" left="1528" right="1597" top="1445">

3.04
</word>
<word bottom="1415" left="1825" right="1895" top="1442">

2'92
</word>
<word bottom="1412" left="2058" right="2074" top="1441">

$
</word>
<word bottom="1412" left="2125" right="2195" top="1440">

2.80
</word>
<word bottom="1385" left="260" right="277" top="1416">

$
</word>
<word bottom="1387" left="340" right="398" top="1414">

386
</word>
<word bottom="1383" left="560" right="576" top="1413">

$
</word>
<word bottom="1385" left="637" right="696" top="1412">

448
</word>
<word bottom="1380" left="859" right="875" top="1410">

$
</word>
<word bottom="1382" left="936" right="997" top="1409">

447
</word>
<word bottom="1378" left="1158" right="1175" top="1408">

$
</word>
<word bottom="1379" left="1236" right="1297" top="1406">

447
</word>
<word bottom="1375" left="1458" right="1475" top="1405">

$
</word>
<word bottom="1377" left="1535" right="1593" top="1404">

431
</word>
<word bottom="1374" left="1834" right="1892" top="1401">

401
</word>
<word bottom="1370" left="2057" right="2073" top="1399">

$
</word>
<word bottom="1372" left="2157" right="2174" top="1398">

7
</word>
<word bottom="1346" left="347" right="423" top="1374">

4.9%
</word>
<word bottom="1344" left="648" right="723" top="1372">

6.2%
</word>
<word bottom="1341" left="948" right="1022" top="1369">

7.6%
</word>
<word bottom="1339" left="1247" right="1321" top="1366">

7.9%
</word>
<word bottom="1336" left="1547" right="1621" top="1364">

7.6%
</word>
<word bottom="1334" left="1846" right="1920" top="1361">

7.7%
</word>
<word bottom="1305" left="310" right="398" top="1333">

126.9
</word>
<word bottom="1303" left="609" right="698" top="1331">

145.4
</word>
<word bottom="1301" left="908" right="997" top="1329">

147.0
</word>
<word bottom="1298" left="1207" right="1296" top="1326">

146.9
</word>
<word bottom="1296" left="1506" right="1596" top="1323">

146.4
</word>
<word bottom="1293" left="1806" right="1891" top="1321">

142.1
</word>
<word bottom="1291" left="2106" right="2219" top="1399">

13367.687%
</word>
<word bottom="1291" left="2167" right="2171" top="1295">

.
</word>
<word bottom="1194" left="260" right="393" top="1228">

$17,381
</word>
<word bottom="1191" left="559" right="696" top="1226">

$17,376
</word>
<word bottom="1189" left="858" right="995" top="1223">

$22,322
</word>
<word bottom="1186" left="1158" right="1292" top="1221">

$21,621
</word>
<word bottom="1184" left="1456" right="1593" top="1219">

$21,555
</word>
<word bottom="1182" left="1755" right="1893" top="1216">

$18,924
</word>
<word bottom="1179" left="2055" right="2191" top="1213">

$18,635
</word>
<word bottom="1157" left="258" right="275" top="1188">

$
</word>
<word bottom="1159" left="336" right="395" top="1186">

663
</word>
<word bottom="1155" left="558" right="574" top="1185">

$
</word>
<word bottom="1150" left="607" right="695" top="1184">

1,052
</word>
<word bottom="1152" left="857" right="874" top="1183">

$
</word>
<word bottom="1148" left="906" right="994" top="1182">

1,125
</word>
<word bottom="1149" left="1157" right="1173" top="1180">

$
</word>
<word bottom="1151" left="1234" right="1293" top="1179">

955
</word>
<word bottom="1147" left="1456" right="1472" top="1178">

$
</word>
<word bottom="1144" left="1505" right="1593" top="1177">

1,582
</word>
<word bottom="1145" left="1755" right="1772" top="1175">

$
</word>
<word bottom="1141" left="1805" right="1894" top="1174">

1,607
</word>
<word bottom="1142" left="2055" right="2071" top="1173">

$
</word>
<word bottom="1138" left="2105" right="2192" top="1172">

1,433
</word>
<word bottom="1118" left="326" right="421" top="1145">

29.7%
</word>
<word bottom="1116" left="607" right="721" top="1144">

107.9%
</word>
<word bottom="1106" left="891" right="1035" top="1142">

(275.0)%
</word>
<word bottom="1110" left="1224" right="1320" top="1138">

45.7%
</word>
<word bottom="1108" left="1524" right="1619" top="1135">

64.6%
</word>
<word bottom="1106" left="1822" right="1918" top="1133">

42.2%
</word>
<word bottom="1103" left="2124" right="2218" top="1131">

57.1%
</word>
<word bottom="1077" left="329" right="420" top="1105">

17.6%
</word>
<word bottom="1075" left="625" right="719" top="1102">

23.0%
</word>
<word bottom="1065" left="932" right="1033" top="1100">

(6.5)%
</word>
<word bottom="1062" left="1231" right="1332" top="1097">

(2.3)%
</word>
<word bottom="1060" left="1530" right="1632" top="1095">

(1.2)%
</word>
<word bottom="1065" left="1844" right="1917" top="1093">

5.8%
</word>
<word bottom="1062" left="2143" right="2216" top="1090">

8.8%
</word>
<word bottom="1031" left="282" right="396" top="1065">

90,000
</word>
<word bottom="1029" left="582" right="696" top="1063">

94,000
</word>
<word bottom="1026" left="864" right="995" top="1060">

104,000
</word>
<word bottom="1024" left="1163" right="1294" top="1057">

101,000
</word>
<word bottom="1021" left="1463" right="1594" top="1054">

111,000
</word>
<word bottom="1020" left="1780" right="1893" top="1052">

98,000
</word>
<word bottom="1016" left="2080" right="2192" top="1050">

97,000
</word>
<word bottom="888" left="257" right="273" top="919">

$
</word>
<word bottom="890" left="334" right="392" top="917">

428
</word>
<word bottom="885" left="555" right="572" top="916">

$
</word>
<word bottom="887" left="636" right="693" top="914">

534
</word>
<word bottom="883" left="855" right="872" top="913">

$
</word>
<word bottom="879" left="905" right="992" top="912">

1,983
</word>
<word bottom="881" left="1154" right="1171" top="911">

$
</word>
<word bottom="876" left="1203" right="1290" top="910">

1,155
</word>
<word bottom="877" left="1454" right="1470" top="908">

$
</word>
<word bottom="880" left="1532" right="1593" top="907">

627
</word>
<word bottom="875" left="1753" right="1769" top="906">

$
</word>
<word bottom="877" left="1831" right="1890" top="905">

263
</word>
<word bottom="873" left="2052" right="2069" top="904">

$
</word>
<word bottom="875" left="2132" right="2189" top="902">

322
</word>
<word bottom="843" left="304" right="394" top="876">

3,194
</word>
<word bottom="840" left="604" right="692" top="874">

3,419
</word>
<word bottom="838" left="901" right="993" top="871">

6,167
</word>
<word bottom="835" left="1200" right="1292" top="869">

6,072
</word>
<word bottom="833" left="1500" right="1592" top="866">

6,407
</word>
<word bottom="832" left="1801" right="1890" top="864">

5,069
</word>
<word bottom="830" left="2100" right="2190" top="862">

5,137
</word>
<word bottom="817" left="358" right="396" top="820">

-
</word>
<word bottom="815" left="658" right="695" top="818">

-
</word>
<word bottom="812" left="957" right="994" top="815">

-
</word>
<word bottom="809" left="1257" right="1294" top="813">

-
</word>
<word bottom="807" left="1556" right="1593" top="810">

-
</word>
<word bottom="805" left="1855" right="1892" top="808">

-
</word>
<word bottom="802" left="2155" right="2191" top="805">

-
</word>
<word bottom="768" left="333" right="392" top="795">

210
</word>
<word bottom="765" left="632" right="692" top="792">

234
</word>
<word bottom="763" left="931" right="990" top="790">

435
</word>
<word bottom="760" left="1231" right="1292" top="787">

697
</word>
<word bottom="758" left="1531" right="1590" top="785">

693
</word>
<word bottom="755" left="1831" right="1889" top="783">

572
</word>
<word bottom="753" left="2131" right="2186" top="780">

591
</word>
<word bottom="721" left="304" right="394" top="755">

3,277
</word>
<word bottom="718" left="603" right="690" top="753">

3,161
</word>
<word bottom="716" left="902" right="991" top="750">

3,773
</word>
<word bottom="714" left="1199" right="1291" top="747">

4,412
</word>
<word bottom="712" left="1499" right="1590" top="745">

4,915
</word>
<word bottom="708" left="1800" right="1890" top="744">

5,338
</word>
<word bottom="706" left="2100" right="2190" top="740">

5,269
</word>
<word bottom="668" left="254" right="271" top="697">

$
</word>
<word bottom="664" left="301" right="392" top="698">

7,109
</word>
<word bottom="666" left="554" right="570" top="697">

$
</word>
<word bottom="662" left="601" right="690" top="696">

7,348
</word>
<word bottom="659" left="853" right="990" top="694">

$12,358
</word>
<word bottom="657" left="1152" right="1290" top="691">

$12,336
</word>
<word bottom="654" left="1452" right="1589" top="688">

$12,642
</word>
<word bottom="651" left="1751" right="1889" top="687">

$11,242
</word>
<word bottom="649" left="2051" right="2188" top="684">

$11,319
</word>
<word bottom="490" left="322" right="415" top="518">

50.9%
</word>
<word bottom="488" left="622" right="714" top="516">

53.8%
</word>
<word bottom="485" left="920" right="1014" top="512">

66.0%
</word>
<word bottom="482" left="1220" right="1313" top="510">

58.6%
</word>
<word bottom="480" left="1519" right="1613" top="508">

55.6%
</word>
<word bottom="477" left="1816" right="1912" top="505">

47.4%
</word>
<word bottom="475" left="2116" right="2211" top="503">

48.2%
</word>
</words>
</ocrresult>

