<?xml version="1.0" encoding="UTF-8" standalone="no"?>
<ocrresult>
<docinfo dpix="300" dpiy="300" height="3300" href="C:\Tomcat6.0\apache-tomcat-6.0.16\webapps\OCRTools\png\1256545586640.png" width="2552"/>
<words>
<word bottom="168" left="180" right="212" top="189">

24
</word>
<word bottom="3097" left="301" right="562" top="3145">
REVIEW</word>
<word bottom="3097" left="582" right="670" top="3145">
OF</word>
<word bottom="3097" left="691" right="1013" top="3146">
ONGOING</word>
<word bottom="3097" left="1033" right="1458" top="3146">
OPERATIONS</word>
<word bottom="2715" left="301" right="473" top="2745">
ANIMAL</word>
<word bottom="2716" left="487" right="655" top="2745">
HEALTH</word>
<word bottom="2440" left="302" right="434" top="2471">
Pfizer's</word>
<word bottom="2440" left="447" right="586" top="2471">
Animal</word>
<word bottom="2440" left="599" right="722" top="2472">
Health</word>
<word bottom="2431" left="735" right="850" top="2471">
Group</word>
<word bottom="2441" left="864" right="892" top="2470">
is</word>
<word bottom="2431" left="905" right="1043" top="2470">
moving</word>
<word bottom="2441" left="1055" right="1179" top="2472">
toward</word>
<word bottom="2394" left="302" right="392" top="2425">
what</word>
<word bottom="2384" left="405" right="573" top="2424">
promises</word>
<word bottom="2394" left="586" right="618" top="2420">
to</word>
<word bottom="2394" left="630" right="672" top="2426">
be</word>
<word bottom="2395" left="685" right="742" top="2426">
the</word>
<word bottom="2395" left="754" right="844" top="2421">
most</word>
<word bottom="2385" left="857" right="1049" top="2426">
significant</word>
<word bottom="2385" left="1061" right="1183" top="2426">
period</word>
<word bottom="2348" left="302" right="338" top="2379">
of</word>
<word bottom="2338" left="347" right="475" top="2380">
growth</word>
<word bottom="2349" left="488" right="523" top="2379">
in</word>
<word bottom="2348" left="536" right="577" top="2378">
its</word>
<word bottom="2339" left="590" right="721" top="2380">
history.</word>
<word bottom="2349" left="736" right="806" top="2380">
The</word>
<word bottom="2338" left="819" right="925" top="2370">
group</word>
<word bottom="2349" left="939" right="967" top="2378">
is</word>
<word bottom="2349" left="981" right="1017" top="2378">
in</word>
<word bottom="2349" left="1029" right="1086" top="2380">
the</word>
<word bottom="2339" left="1100" right="1190" top="2380">
early</word>
<word bottom="2292" left="302" right="407" top="2329">
stages</word>
<word bottom="2303" left="421" right="457" top="2334">
of</word>
<word bottom="2293" left="467" right="685" top="2334">
introducing</word>
<word bottom="2303" left="697" right="790" top="2334">
three</word>
<word bottom="2294" left="803" right="908" top="2333">
major</word>
<word bottom="2303" left="920" right="997" top="2323">
new</word>
<word bottom="2293" left="1009" right="1213" top="2334">
products—</word>
<word bottom="2253" left="301" right="495" top="2285">

Dectomax,
</word>
<word bottom="2257" left="508" right="663" top="2288">

Advocin
</word>
<word bottom="2257" left="676" right="744" top="2289">
and</word>
<word bottom="2256" left="756" right="1036" top="2288">

Aviax—around
</word>
<word bottom="2257" left="1048" right="1105" top="2288">
the</word>
<word bottom="2257" left="1117" right="1234" top="2289">
world.</word>
<word bottom="2211" left="302" right="411" top="2242">
These</word>
<word bottom="2211" left="425" right="615" top="2241">
innovative</word>
<word bottom="2201" left="628" right="788" top="2243">
products</word>
<word bottom="2212" left="802" right="871" top="2243">
add</word>
<word bottom="2201" left="884" right="1077" top="2242">
significant</word>
<word bottom="2211" left="1089" right="1195" top="2243">
thera-</word>
<word bottom="2155" left="302" right="418" top="2195">
peutic</word>
<word bottom="2165" left="430" right="529" top="2197">
value</word>
<word bottom="2165" left="542" right="574" top="2191">
to</word>
<word bottom="2165" left="586" right="643" top="2197">
the</word>
<word bottom="2155" left="657" right="803" top="2195">
practice</word>
<word bottom="2166" left="817" right="853" top="2197">
of</word>
<word bottom="2165" left="862" right="989" top="2197">
animal</word>
<word bottom="2156" left="1002" right="1204" top="2197">
husbandry.</word>
<word bottom="2109" left="302" right="397" top="2150">
They,</word>
<word bottom="2110" left="412" right="512" top="2151">
along</word>
<word bottom="2119" left="524" right="609" top="2151">
with</word>
<word bottom="2119" left="621" right="678" top="2151">
the</word>
<word bottom="2119" left="691" right="860" top="2152">
technical</word>
<word bottom="2119" left="874" right="1058" top="2149">
assistance</word>
<word bottom="2120" left="1072" right="1206" top="2152">
needed</word>
<word bottom="2073" left="302" right="334" top="2099">
to</word>
<word bottom="2073" left="347" right="409" top="2094">
use</word>
<word bottom="2073" left="421" right="515" top="2105">
them</word>
<word bottom="2073" left="529" right="578" top="2104">
for</word>
<word bottom="2073" left="589" right="663" top="2105">
best</word>
<word bottom="2069" left="674" right="805" top="2105">
results,</word>
<word bottom="2074" left="819" right="892" top="2106">
will</word>
<word bottom="2073" left="904" right="945" top="2106">
be</word>
<word bottom="2063" left="959" right="1143" top="2103">
important</word>
<word bottom="2074" left="1156" right="1251" top="2106">
addi-</word>
<word bottom="2026" left="302" right="393" top="2056">
tions</word>
<word bottom="2027" left="406" right="438" top="2054">
to</word>
<word bottom="2027" left="451" right="508" top="2059">
the</word>
<word bottom="2027" left="521" right="591" top="2059">
line</word>
<word bottom="2027" left="605" right="641" top="2059">
of</word>
<word bottom="2017" left="649" right="811" top="2059">
products</word>
<word bottom="2027" left="824" right="940" top="2060">
which</word>
<word bottom="2027" left="953" right="1010" top="2059">
the</word>
<word bottom="2028" left="1022" right="1162" top="2059">
Animal</word>
<word bottom="1981" left="302" right="425" top="2012">
Health</word>
<word bottom="1971" left="438" right="552" top="2011">
Group</word>
<word bottom="1981" left="566" right="708" top="2013">
markets</word>
<word bottom="1981" left="721" right="753" top="2008">
to</word>
<word bottom="1982" left="766" right="823" top="2013">
the</word>
<word bottom="1972" left="836" right="922" top="2013">
large</word>
<word bottom="1971" left="935" right="1120" top="2013">
producers</word>
<word bottom="1982" left="1134" right="1170" top="2013">
of</word>
<word bottom="1935" left="303" right="383" top="1967">
food</word>
<word bottom="1935" left="396" right="551" top="1967">
animals.</word>
<word bottom="1879" left="352" right="615" top="1921">
Operationally,</word>
<word bottom="1890" left="632" right="717" top="1917">

1993
</word>
<word bottom="1890" left="733" right="801" top="1910">
was</word>
<word bottom="1890" left="815" right="858" top="1911">
an</word>
<word bottom="1880" left="872" right="1017" top="1919">
exciting</word>
<word bottom="1880" left="1030" right="1110" top="1910">
year.</word>
<word bottom="1890" left="1126" right="1180" top="1919">
We</word>
<word bottom="1843" left="303" right="477" top="1875">
launched</word>
<word bottom="1843" left="490" right="675" top="1873">

Dectomax
</word>
<word bottom="1844" left="689" right="725" top="1873">
in</word>
<word bottom="1844" left="738" right="779" top="1874">
its</word>
<word bottom="1845" left="793" right="863" top="1876">
first</word>
<word bottom="1844" left="876" right="1029" top="1875">
markets.</word>
<word bottom="1844" left="1044" right="1200" top="1875">

Advocin
</word>
<word bottom="1797" left="303" right="391" top="1829">
sales</word>
<word bottom="1797" left="406" right="597" top="1829">
continued</word>
<word bottom="1798" left="609" right="642" top="1824">
to</word>
<word bottom="1788" left="656" right="802" top="1830">
expand,</word>
<word bottom="1799" left="817" right="885" top="1830">
and</word>
<word bottom="1798" left="899" right="987" top="1829">
sales</word>
<word bottom="1798" left="1002" right="1038" top="1829">
of</word>
<word bottom="1798" left="1048" right="1172" top="1829">
in-line</word>
<word bottom="1741" left="303" right="465" top="1783">
products</word>
<word bottom="1752" left="478" right="693" top="1784">
maintained</word>
<word bottom="1752" left="706" right="872" top="1784">
excellent</word>
<word bottom="1752" left="885" right="997" top="1784">
levels.</word>
<word bottom="1752" left="1012" right="1067" top="1781">
We</word>
<word bottom="1752" left="1081" right="1153" top="1784">
also</word>
<word bottom="1696" left="301" right="409" top="1737">
began</word>
<word bottom="1706" left="423" right="441" top="1727">
a</word>
<word bottom="1706" left="454" right="600" top="1737">
number</word>
<word bottom="1706" left="613" right="649" top="1737">
of</word>
<word bottom="1697" left="658" right="901" top="1736">
restructuring</word>
<word bottom="1696" left="914" right="1058" top="1736">
projects</word>
<word bottom="1707" left="1071" right="1189" top="1738">
which</word>
<word bottom="1660" left="303" right="353" top="1680">
we</word>
<word bottom="1650" left="367" right="486" top="1687">
expect</word>
<word bottom="1660" left="498" right="572" top="1691">
will</word>
<word bottom="1660" left="586" right="777" top="1692">
contribute</word>
<word bottom="1651" left="791" right="1024" top="1692">
significantly</word>
<word bottom="1660" left="1036" right="1069" top="1686">
to</word>
<word bottom="1661" left="1083" right="1145" top="1681">
our</word>
<word bottom="1614" left="303" right="413" top="1645">
future</word>
<word bottom="1604" left="427" right="652" top="1646">
profitability.</word>
<word bottom="1615" left="667" right="697" top="1644">
A</word>
<word bottom="1605" left="710" right="816" top="1645">
major</word>
<word bottom="1614" left="830" right="979" top="1647">
element</word>
<word bottom="1614" left="993" right="1029" top="1646">
of</word>
<word bottom="1615" left="1040" right="1101" top="1635">
our</word>
<word bottom="1615" left="1113" right="1255" top="1641">
restruc-</word>
<word bottom="1559" left="302" right="415" top="1598">
turing</word>
<word bottom="1569" left="438" right="507" top="1589">
was</word>
<word bottom="1568" left="520" right="578" top="1600">
the</word>
<word bottom="1568" left="591" right="774" top="1600">
formation</word>
<word bottom="1569" left="788" right="824" top="1601">
of</word>
<word bottom="1569" left="834" right="891" top="1601">
the</word>
<word bottom="1568" left="904" right="1013" top="1600">
North</word>
<word bottom="1569" left="1026" right="1210" top="1599">
American</word>
<word bottom="1522" left="302" right="443" top="1554">
Animal</word>
<word bottom="1522" left="456" right="581" top="1555">
Health</word>
<word bottom="1518" left="593" right="762" top="1552">
Division,</word>
<word bottom="1523" left="777" right="795" top="1544">
a</word>
<word bottom="1513" left="809" right="896" top="1555">
fully</word>
<word bottom="1512" left="909" right="1092" top="1554">
integrated</word>
<word bottom="1513" left="1107" right="1222" top="1543">
opera-</word>
<word bottom="1476" left="302" right="376" top="1506">
tion</word>
<word bottom="1467" left="390" right="525" top="1506">
serving</word>
<word bottom="1476" left="538" right="595" top="1508">
the</word>
<word bottom="1476" left="609" right="684" top="1507">
U.S.</word>
<word bottom="1477" left="701" right="769" top="1509">
and</word>
<word bottom="1476" left="782" right="929" top="1509">
Canada.</word>
<word bottom="1466" left="945" right="994" top="1506">
By</word>
<word bottom="1467" left="1006" right="1145" top="1506">
moving</word>
<word bottom="1477" left="1158" right="1215" top="1508">
the</word>
<word bottom="1420" left="303" right="544" top="1462">
headquarters</word>
<word bottom="1430" left="559" right="595" top="1462">
of</word>
<word bottom="1430" left="604" right="673" top="1462">
this</word>
<word bottom="1431" left="687" right="763" top="1451">
new</word>
<word bottom="1431" left="777" right="930" top="1463">
division</word>
<word bottom="1430" left="943" right="975" top="1457">
to</word>
<word bottom="1431" left="990" right="1075" top="1460">
Lee's</word>
<word bottom="1427" left="1090" right="1249" top="1461">
Summit,</word>
<word bottom="1384" left="303" right="638" top="1416">
Missouri—within</word>
<word bottom="1380" left="653" right="751" top="1412">

1,000
</word>
<word bottom="1385" left="765" right="866" top="1417">
miles</word>
<word bottom="1385" left="880" right="916" top="1416">
of</word>
<word bottom="1385" left="927" right="971" top="1416">
all</word>
<word bottom="1385" left="986" right="1047" top="1405">
our</word>
<word bottom="1376" left="1060" right="1167" top="1414">
major</word>
<word bottom="1385" left="1180" right="1255" top="1406">
cus-</word>
<word bottom="1339" left="303" right="522" top="1365">
tomers—we</word>
<word bottom="1339" left="535" right="618" top="1370">
have</word>
<word bottom="1339" left="631" right="732" top="1371">
made</word>
<word bottom="1339" left="746" right="771" top="1369">
it</word>
<word bottom="1329" left="784" right="938" top="1371">
possible</word>
<word bottom="1339" left="952" right="1002" top="1370">
for</word>
<word bottom="1339" left="1015" right="1077" top="1360">
our</word>
<word bottom="1339" left="1090" right="1205" top="1369">
senior</word>
<word bottom="1283" left="303" right="542" top="1319">
management</word>
<word bottom="1293" left="554" right="587" top="1319">
to</word>
<word bottom="1293" left="600" right="694" top="1325">
work</word>
<word bottom="1293" left="705" right="799" top="1314">
more</word>
<word bottom="1283" left="813" right="944" top="1325">
closely</word>
<word bottom="1293" left="957" right="1042" top="1325">
with</word>
<word bottom="1293" left="1055" right="1112" top="1325">
the</word>
<word bottom="1284" left="1126" right="1245" top="1325">
largest</word>
<word bottom="1247" left="303" right="384" top="1279">
food</word>
<word bottom="1237" left="397" right="595" top="1279">
producers,</word>
<word bottom="1247" left="609" right="715" top="1279">
while</word>
<word bottom="1248" left="729" right="760" top="1274">
at</word>
<word bottom="1248" left="773" right="830" top="1279">
the</word>
<word bottom="1247" left="844" right="937" top="1268">
same</word>
<word bottom="1247" left="951" right="1033" top="1277">
time</word>
<word bottom="1238" left="1046" right="1212" top="1279">
reducing</word>
<word bottom="1201" left="303" right="391" top="1227">
costs</word>
<word bottom="1201" left="406" right="474" top="1233">
and</word>
<word bottom="1191" left="488" right="680" top="1231">
improving</word>
<word bottom="1192" left="694" right="880" top="1233">
efficiency</word>
<word bottom="1145" left="352" right="543" top="1186">
Beginning</word>
<word bottom="1155" left="557" right="593" top="1185">
in</word>
<word bottom="1151" left="608" right="706" top="1183">

1994,
</word>
<word bottom="1156" left="720" right="777" top="1187">
the</word>
<word bottom="1155" left="791" right="931" top="1187">
Animal</word>
<word bottom="1155" left="944" right="1069" top="1187">
Health</word>
<word bottom="1146" left="1082" right="1198" top="1185">
Group</word>
<word bottom="1099" left="303" right="438" top="1136">
expects</word>
<word bottom="1110" left="451" right="484" top="1136">
to</word>
<word bottom="1109" left="497" right="621" top="1141">
realize</word>
<word bottom="1100" left="635" right="831" top="1141">
significant</word>
<word bottom="1100" left="843" right="972" top="1141">
growth</word>
<word bottom="1110" left="986" right="1021" top="1139">
in</word>
<word bottom="1109" left="1033" right="1117" top="1141">
both</word>
<word bottom="1110" left="1131" right="1219" top="1141">
sales</word>
<word bottom="1063" left="304" right="372" top="1095">
and</word>
<word bottom="1053" left="385" right="494" top="1095">
profit.</word>
<word bottom="1063" left="509" right="592" top="1093">
New</word>
<word bottom="1053" left="605" right="767" top="1095">
products</word>
<word bottom="1064" left="782" right="910" top="1096">
should</word>
<word bottom="1063" left="924" right="1071" top="1090">
account</word>
<word bottom="1064" left="1085" right="1135" top="1095">
for</word>
<word bottom="1064" left="1148" right="1178" top="1090">
at</word>
<word bottom="1017" left="304" right="387" top="1049">
least</word>
<word bottom="1018" left="400" right="443" top="1045">

40
</word>
<word bottom="1008" left="457" right="597" top="1044">
percent</word>
<word bottom="1017" left="611" right="647" top="1049">
of</word>
<word bottom="1018" left="656" right="859" top="1050">
worldwide</word>
<word bottom="1017" left="874" right="962" top="1049">
sales</word>
<word bottom="1008" left="974" right="1017" top="1049">
by</word>
<word bottom="1018" left="1032" right="1129" top="1045">

1998.
</word>
<word bottom="1018" left="1144" right="1181" top="1047">
In</word>
<word bottom="967" left="304" right="472" top="1003">
addition,</word>
<word bottom="971" left="487" right="563" top="993">
new</word>
<word bottom="962" left="577" right="660" top="1003">
drug</word>
<word bottom="972" left="674" right="873" top="1004">
candidates</word>
<word bottom="961" left="888" right="1025" top="1003">
already</word>
<word bottom="972" left="1038" right="1074" top="1001">
in</word>
<word bottom="972" left="1088" right="1150" top="992">
our</word>
<word bottom="972" left="1164" right="1231" top="1003">
dis-</word>
<word bottom="916" left="304" right="423" top="946">
covery</word>
<word bottom="925" left="436" right="592" top="957">
research</word>
<word bottom="926" left="605" right="764" top="957">
facilities</word>
<word bottom="926" left="778" right="863" top="958">
hold</word>
<word bottom="925" left="876" right="933" top="958">
the</word>
<word bottom="915" left="947" right="1098" top="955">
promise</word>
<word bottom="926" left="1112" right="1148" top="957">
of</word>
<word bottom="926" left="1159" right="1177" top="946">
a</word>
<word bottom="879" left="303" right="506" top="912">
substantial</word>
<word bottom="869" left="519" right="675" top="911">
pipeline</word>
<word bottom="880" left="690" right="727" top="911">
of</word>
<word bottom="880" left="735" right="812" top="901">
new</word>
<word bottom="870" left="825" right="987" top="912">
products</word>
<word bottom="880" left="1000" right="1078" top="911">
well</word>
<word bottom="880" left="1093" right="1163" top="909">
into</word>
<word bottom="880" left="1177" right="1234" top="912">
the</word>
<word bottom="834" left="303" right="381" top="860">
next</word>
<word bottom="825" left="394" right="540" top="861">
century</word>
<word bottom="788" left="352" right="536" top="817">

Dectomax
</word>
<word bottom="788" left="549" right="576" top="817">
is</word>
<word bottom="788" left="590" right="646" top="819">
the</word>
<word bottom="788" left="659" right="748" top="815">
most</word>
<word bottom="779" left="761" right="945" top="818">
important</word>
<word bottom="788" left="958" right="994" top="819">
of</word>
<word bottom="788" left="1005" right="1065" top="809">
our</word>
<word bottom="788" left="1078" right="1153" top="808">
new</word>
<word bottom="732" left="303" right="473" top="774">
products.</word>
<word bottom="743" left="488" right="513" top="772">
It</word>
<word bottom="742" left="525" right="586" top="774">
has</word>
<word bottom="742" left="600" right="618" top="763">
a</word>
<word bottom="742" left="629" right="772" top="774">
broader</word>
<word bottom="733" left="784" right="957" top="769">
spectrum</word>
<word bottom="742" left="970" right="1006" top="773">
of</word>
<word bottom="733" left="1016" right="1154" top="772">
activity</word>
<word bottom="686" left="304" right="431" top="726">
against</word>
<word bottom="687" left="444" right="604" top="726">
parasites</word>
<word bottom="696" left="617" right="700" top="728">
than</word>
<word bottom="687" left="713" right="778" top="717">
any</word>
<word bottom="697" left="792" right="887" top="729">
other</word>
<word bottom="696" left="899" right="1026" top="728">
animal</word>
<word bottom="697" left="1039" right="1156" top="728">
health</word>
<word bottom="640" left="303" right="457" top="682">
product,</word>
<word bottom="651" left="472" right="540" top="682">
and</word>
<word bottom="650" left="553" right="578" top="680">
it</word>
<word bottom="650" left="590" right="618" top="680">
is</word>
<word bottom="651" left="633" right="784" top="682">
effective</word>
<word bottom="641" left="798" right="913" top="683">
longer</word>
<word bottom="650" left="926" right="961" top="671">
as</word>
<word bottom="651" left="974" right="1061" top="682">
well.</word>
<word bottom="604" left="303" right="357" top="634">
We</word>
<word bottom="604" left="370" right="574" top="637">
introduced</word>
<word bottom="604" left="587" right="771" top="634">

Dectomax
</word>
<word bottom="605" left="783" right="819" top="635">
in</word>
<word bottom="600" left="832" right="951" top="636">
Brazil,</word>
<word bottom="548" left="303" right="486" top="589">
Argentina</word>
<word bottom="558" left="499" right="567" top="590">
and</word>
<word bottom="558" left="581" right="689" top="590">
South</word>
<word bottom="559" left="702" right="816" top="590">
Africa</word>
<word bottom="560" left="829" right="865" top="589">
in</word>
<word bottom="558" left="877" right="933" top="591">
the</word>
<word bottom="558" left="948" right="1077" top="590">
second</word>
<word bottom="512" left="303" right="377" top="544">
half</word>
<word bottom="512" left="386" right="423" top="544">
of</word>
<word bottom="513" left="434" right="519" top="540">

1993
</word>
<word bottom="512" left="533" right="617" top="544">
with</word>
<word bottom="512" left="630" right="765" top="544">
notable</word>
<word bottom="512" left="779" right="926" top="534">
success.</word>
<word bottom="466" left="303" right="495" top="496">
Customers</word>
<word bottom="466" left="509" right="590" top="498">
have</word>
<word bottom="466" left="605" right="725" top="498">
shown</word>
<word bottom="457" left="737" right="953" top="499">
widespread</word>
<word bottom="466" left="967" right="1087" top="498">
enthu-</word>
<word bottom="420" left="304" right="407" top="450">
siasm</word>
<word bottom="421" left="421" right="523" top="452">
about</word>
<word bottom="420" left="535" right="614" top="452">
how</word>
<word bottom="421" left="626" right="703" top="452">
well</word>
<word bottom="421" left="716" right="803" top="452">
their</word>
<word bottom="420" left="816" right="960" top="452">
animals</word>
<word bottom="420" left="974" right="1028" top="441">
are</word>
<word bottom="2707" left="1352" right="1455" top="2747">
doing</word>
<word bottom="2716" left="1469" right="1514" top="2737">
on</word>
<word bottom="2717" left="1526" right="1583" top="2748">
the</word>
<word bottom="2707" left="1596" right="1749" top="2747">
product.</word>
<word bottom="2716" left="1764" right="1835" top="2748">
The</word>
<word bottom="2707" left="1848" right="1939" top="2748">
early</word>
<word bottom="2716" left="1952" right="2090" top="2738">
success</word>
<word bottom="2717" left="2104" right="2141" top="2748">
of</word>
<word bottom="2670" left="1350" right="1534" top="2699">

Dectomax
</word>
<word bottom="2671" left="1547" right="1583" top="2700">
in</word>
<word bottom="2666" left="1595" right="1714" top="2702">
Brazil,</word>
<word bottom="2670" left="1727" right="1784" top="2702">
the</word>
<word bottom="2671" left="1797" right="1929" top="2703">
world's</word>
<word bottom="2661" left="1943" right="2207" top="2702">
second-largest</word>
<word bottom="2671" left="2220" right="2283" top="2697">
cat-</word>
<word bottom="2624" left="1350" right="1395" top="2656">
tle</word>
<word bottom="2620" left="1408" right="1544" top="2656">
market,</word>
<word bottom="2625" left="1559" right="1587" top="2654">
is</word>
<word bottom="2625" left="1601" right="1619" top="2645">
a</word>
<word bottom="2614" left="1632" right="1826" top="2656">
significant</word>
<word bottom="2625" left="1838" right="2004" top="2657">
indicator</word>
<word bottom="2625" left="2018" right="2054" top="2656">
of</word>
<word bottom="2625" left="2063" right="2103" top="2654">
its</word>
<word bottom="2615" left="2117" right="2290" top="2657">
potential.</word>
<word bottom="2579" left="1402" right="1497" top="2610">
Sales</word>
<word bottom="2579" left="1511" right="1548" top="2610">
of</word>
<word bottom="2574" left="1557" right="1723" top="2611">

Advocin,
</word>
<word bottom="2579" left="1738" right="1800" top="2599">
our</word>
<word bottom="2569" left="1812" right="2115" top="2610">

fluoroquinolone
</word>
<word bottom="2579" left="2129" right="2278" top="2611">
antibac-</word>
<word bottom="2533" left="1350" right="1445" top="2564">
terial</word>
<word bottom="2532" left="1460" right="1509" top="2564">
for</word>
<word bottom="2528" left="1523" right="1696" top="2565">
livestock,</word>
<word bottom="2533" left="1711" right="1890" top="2565">
increased</word>
<word bottom="2523" left="1904" right="2136" top="2565">
significantly</word>
<word bottom="2534" left="2149" right="2186" top="2563">
in</word>
<word bottom="2533" left="2201" right="2286" top="2561">

1993
</word>
<word bottom="2477" left="1352" right="1476" top="2518">
largely</word>
<word bottom="2487" left="1490" right="1535" top="2507">
on</word>
<word bottom="2487" left="1547" right="1605" top="2519">
the</word>
<word bottom="2477" left="1619" right="1769" top="2518">
strength</word>
<word bottom="2487" left="1783" right="1819" top="2519">
of</word>
<word bottom="2487" left="1829" right="1869" top="2517">
its</word>
<word bottom="2487" left="1884" right="2076" top="2518">
successful</word>
<word bottom="2487" left="2091" right="2264" top="2519">
introduc-</word>
<word bottom="2441" left="1351" right="1425" top="2470">
tion</word>
<word bottom="2441" left="1438" right="1475" top="2470">
in</word>
<word bottom="2431" left="1486" right="1601" top="2470">
Japan.</word>
<word bottom="2441" left="1616" right="1687" top="2473">
The</word>
<word bottom="2431" left="1701" right="1847" top="2472">
product</word>
<word bottom="2441" left="1860" right="1888" top="2471">
is</word>
<word bottom="2442" left="1902" right="1981" top="2462">
now</word>
<word bottom="2441" left="1994" right="2157" top="2472">
available</word>
<word bottom="2385" left="1351" right="1560" top="2427">
throughout</word>
<word bottom="2395" left="1573" right="1662" top="2421">
most</word>
<word bottom="2395" left="1676" right="1712" top="2426">
of</word>
<word bottom="2395" left="1722" right="1818" top="2424">
Latin</word>
<word bottom="2394" left="1830" right="2000" top="2425">
America,</word>
<word bottom="2395" left="2014" right="2130" top="2426">
Africa</word>
<word bottom="2395" left="2143" right="2212" top="2427">
and</word>
<word bottom="2349" left="1351" right="1442" top="2378">
Asia.</word>
<word bottom="2339" left="1458" right="1507" top="2378">
By</word>
<word bottom="2349" left="1520" right="1583" top="2381">
late</word>
<word bottom="2344" left="1599" right="1697" top="2377">

1995,
</word>
<word bottom="2349" left="1711" right="1761" top="2369">
we</word>
<word bottom="2339" left="1775" right="1894" top="2375">
expect</word>
<word bottom="2350" left="1907" right="1939" top="2376">
to</word>
<word bottom="2340" left="1952" right="2053" top="2381">
begin</word>
<word bottom="2339" left="2066" right="2191" top="2381">
rolling</word>
<word bottom="2349" left="2204" right="2228" top="2379">
it</word>
<word bottom="2349" left="2242" right="2302" top="2376">
out</word>
<word bottom="2303" left="1351" right="1387" top="2332">
in</word>
<word bottom="2303" left="1400" right="1457" top="2334">
the</word>
<word bottom="2294" left="1471" right="1558" top="2334">
large</word>
<word bottom="2303" left="1571" right="1714" top="2335">
markets</word>
<word bottom="2303" left="1729" right="1765" top="2334">
of</word>
<word bottom="2294" left="1775" right="1907" top="2332">
Europe</word>
<word bottom="2304" left="1922" right="1989" top="2335">
and</word>
<word bottom="2303" left="2003" right="2060" top="2335">
the</word>
<word bottom="2299" left="2073" right="2162" top="2333">
U.S.,</word>
<word bottom="2303" left="2176" right="2290" top="2335">
where</word>
<word bottom="2247" left="1351" right="1553" top="2287">
respiratory</word>
<word bottom="2257" left="1567" right="1701" top="2289">
disease</word>
<word bottom="2257" left="1715" right="1743" top="2287">
is</word>
<word bottom="2258" left="1758" right="1776" top="2278">
a</word>
<word bottom="2248" left="1788" right="1895" top="2287">
major</word>
<word bottom="2248" left="1908" right="2073" top="2289">
problem.</word>
<word bottom="2207" left="1401" right="1516" top="2241">

Aviax,
</word>
<word bottom="2212" left="1531" right="1549" top="2232">
a</word>
<word bottom="2211" left="1561" right="1882" top="2244">
Pfizer-discovered</word>
<word bottom="2202" left="1895" right="2042" top="2244">
product</word>
<word bottom="2212" left="2055" right="2105" top="2243">
for</word>
<word bottom="2212" left="2117" right="2174" top="2243">
the</word>
<word bottom="2212" left="2188" right="2282" top="2238">
treat-</word>
<word bottom="2165" left="1351" right="1446" top="2192">
ment</word>
<word bottom="2166" left="1460" right="1496" top="2197">
of</word>
<word bottom="2165" left="1506" right="1714" top="2198">

coccidiosis
</word>
<word bottom="2166" left="1729" right="1765" top="2195">
in</word>
<word bottom="2162" left="1778" right="1953" top="2198">
chickens,</word>
<word bottom="2166" left="1968" right="2096" top="2198">
should</word>
<word bottom="2166" left="2108" right="2150" top="2197">
be</word>
<word bottom="2166" left="2164" right="2266" top="2196">
intro-</word>
<word bottom="2120" left="1353" right="1466" top="2151">
duced</word>
<word bottom="2110" left="1481" right="1614" top="2152">
shortly.</word>
<word bottom="2119" left="1630" right="1655" top="2150">
It</word>
<word bottom="2120" left="1667" right="1729" top="2151">
has</word>
<word bottom="2110" left="1743" right="1881" top="2152">
already</word>
<word bottom="2120" left="1892" right="1981" top="2152">
been</word>
<word bottom="2110" left="1994" right="2167" top="2152">
approved</word>
<word bottom="2120" left="2180" right="2216" top="2150">
in</word>
<word bottom="2073" left="1351" right="1441" top="2100">
most</word>
<word bottom="2074" left="1454" right="1491" top="2105">
of</word>
<word bottom="2074" left="1500" right="1597" top="2104">
Latin</word>
<word bottom="2074" left="1609" right="1777" top="2104">
America.</word>
<word bottom="2074" left="1793" right="1898" top="2104">

Aviax
</word>
<word bottom="2074" left="1910" right="1984" top="2106">
will</word>
<word bottom="2064" left="1998" right="2233" top="2105">
complement</word>
<word bottom="2023" left="1352" right="1517" top="2057">

Coxistac,
</word>
<word bottom="2028" left="1532" right="1550" top="2048">
a</word>
<word bottom="2027" left="1564" right="1720" top="2060">
licensed</word>
<word bottom="2028" left="1733" right="1977" top="2060">

anticoccidial
</word>
<word bottom="2028" left="1990" right="2108" top="2059">
which</word>
<word bottom="2028" left="2121" right="2171" top="2048">
we</word>
<word bottom="2028" left="2184" right="2269" top="2049">
mar-</word>
<word bottom="1981" left="1351" right="1404" top="2013">
ket</word>
<word bottom="1982" left="1417" right="1553" top="2014">
outside</word>
<word bottom="1982" left="1567" right="1624" top="2014">
the</word>
<word bottom="1981" left="1637" right="1713" top="2012">
U.S.</word>
<word bottom="1982" left="1729" right="1797" top="2013">
and</word>
<word bottom="1972" left="1810" right="1953" top="2011">
Europe.</word>
<word bottom="1982" left="1969" right="2071" top="2012">
Since</word>
<word bottom="1972" left="2085" right="2223" top="2013">
poultry</word>
<word bottom="1925" left="1351" right="1538" top="1967">
producers</word>
<word bottom="1926" left="1551" right="1723" top="1967">
generally</word>
<word bottom="1936" left="1736" right="1837" top="1962">
rotate</word>
<word bottom="1936" left="1850" right="1939" top="1968">
their</word>
<word bottom="1936" left="1951" right="2058" top="1968">
flocks</word>
<word bottom="1936" left="2071" right="2226" top="1967">
between</word>
<word bottom="1890" left="1351" right="1444" top="1921">
three</word>
<word bottom="1890" left="1459" right="1495" top="1910">
or</word>
<word bottom="1890" left="1508" right="1583" top="1922">
four</word>
<word bottom="1886" left="1596" right="1869" top="1922">

anticoccidials,
</word>
<word bottom="1891" left="1884" right="1908" top="1920">
it</word>
<word bottom="1891" left="1921" right="1995" top="1922">
will</word>
<word bottom="1890" left="2009" right="2164" top="1921">
enhance</word>
<word bottom="1890" left="2179" right="2241" top="1911">
our</word>
<word bottom="1844" left="1352" right="1440" top="1875">
sales</word>
<word bottom="1834" left="1455" right="1710" top="1874">
opportunities</word>
<word bottom="1844" left="1723" right="1837" top="1876">
where</word>
<word bottom="1845" left="1850" right="1901" top="1865">
we</word>
<word bottom="1844" left="1914" right="2041" top="1876">
market</word>
<word bottom="1844" left="2054" right="2209" top="1874">

Coxistac
</word>
<word bottom="1845" left="2223" right="2292" top="1876">
and</word>
<word bottom="1798" left="1351" right="1425" top="1830">
will</word>
<word bottom="1788" left="1439" right="1530" top="1819">
open</word>
<word bottom="1789" left="1543" right="1590" top="1819">
up</word>
<word bottom="1799" left="1605" right="1623" top="1819">
a</word>
<word bottom="1798" left="1636" right="1750" top="1830">
whole</word>
<word bottom="1798" left="1764" right="1840" top="1819">
new</word>
<word bottom="1799" left="1852" right="2013" top="1830">
business</word>
<word bottom="1798" left="2028" right="2077" top="1829">
for</word>
<word bottom="1799" left="2090" right="2197" top="1830">
Pfizer</word>
<word bottom="1799" left="2210" right="2246" top="1828">
in</word>
<word bottom="1752" left="1351" right="1450" top="1784">
those</word>
<word bottom="1752" left="1464" right="1638" top="1783">
countries</word>
<word bottom="1752" left="1651" right="1766" top="1784">
where</word>
<word bottom="1753" left="1779" right="1830" top="1773">
we</word>
<word bottom="1753" left="1845" right="1888" top="1784">
do</word>
<word bottom="1753" left="1902" right="1970" top="1779">
not.</word>
<word bottom="1707" left="1402" right="1438" top="1736">
In</word>
<word bottom="1706" left="1452" right="1611" top="1738">
addition</word>
<word bottom="1707" left="1623" right="1656" top="1733">
to</word>
<word bottom="1697" left="1670" right="1890" top="1738">
introducing</word>
<word bottom="1706" left="1903" right="2096" top="1737">
innovative</word>
<word bottom="1707" left="2109" right="2185" top="1727">
new</word>
<word bottom="1697" left="2199" right="2298" top="1738">
prod-</word>
<word bottom="1660" left="1351" right="1425" top="1687">
ucts</word>
<word bottom="1651" left="1440" right="1630" top="1693">
developed</word>
<word bottom="1651" left="1642" right="1685" top="1693">
by</word>
<word bottom="1661" left="1699" right="1760" top="1681">
our</word>
<word bottom="1657" left="1773" right="1993" top="1692">
researchers,</word>
<word bottom="1661" left="2007" right="2064" top="1692">
the</word>
<word bottom="1661" left="2077" right="2218" top="1693">
Animal</word>
<word bottom="1615" left="1351" right="1475" top="1646">
Health</word>
<word bottom="1605" left="1489" right="1604" top="1645">
Group</word>
<word bottom="1615" left="1619" right="1647" top="1645">
is</word>
<word bottom="1605" left="1661" right="1813" top="1646">
working</word>
<word bottom="1615" left="1827" right="1911" top="1647">
hard</word>
<word bottom="1615" left="1923" right="1956" top="1642">
to</word>
<word bottom="1605" left="1970" right="2121" top="1645">
improve</word>
<word bottom="1615" left="2134" right="2191" top="1647">
the</word>
<word bottom="1605" left="2205" right="2292" top="1647">
prof-</word>
<word bottom="1559" left="1352" right="1498" top="1600">
itability</word>
<word bottom="1569" left="1512" right="1548" top="1601">
of</word>
<word bottom="1569" left="1558" right="1599" top="1599">
its</word>
<word bottom="1559" left="1613" right="1757" top="1598">
existing</word>
<word bottom="1569" left="1770" right="1878" top="1601">
world</word>
<word bottom="1569" left="1891" right="2034" top="1601">
markets</word>
<word bottom="1569" left="2049" right="2117" top="1600">
and</word>
<word bottom="1559" left="2130" right="2303" top="1601">
products.</word>
<word bottom="1522" left="1352" right="1423" top="1552">
Our</word>
<word bottom="1513" left="1436" right="1581" top="1555">
flagship</word>
<word bottom="1523" left="1595" right="1719" top="1555">
in-line</word>
<word bottom="1513" left="1733" right="1888" top="1555">
product,</word>
<word bottom="1518" left="1903" right="2051" top="1555">
TM/LA,</word>
<word bottom="1523" left="2066" right="2257" top="1555">
continued</word>
<word bottom="1523" left="2270" right="2303" top="1550">
to</word>
<word bottom="1477" left="1352" right="1448" top="1508">
show</word>
<word bottom="1477" left="1462" right="1628" top="1509">
excellent</word>
<word bottom="1467" left="1640" right="2034" top="1509">
growth—particularly</word>
<word bottom="1477" left="2048" right="2084" top="1506">
in</word>
<word bottom="1477" left="2097" right="2154" top="1508">
the</word>
<word bottom="1477" left="2167" right="2267" top="1506">
West-</word>
<word bottom="1431" left="1352" right="1411" top="1451">
ern</word>
<word bottom="1421" left="1424" right="1660" top="1463">
Hemisphere,</word>
<word bottom="1431" left="1674" right="1787" top="1462">
where</word>
<word bottom="1431" left="1801" right="1888" top="1463">
sales</word>
<word bottom="1431" left="1902" right="2078" top="1462">
increased</word>
<word bottom="1421" left="2090" right="2132" top="1462">
by</word>
<word bottom="1431" left="2147" right="2187" top="1458">

29
</word>
<word bottom="1421" left="2201" right="2273" top="1452">
per-</word>
<word bottom="1385" left="1352" right="1438" top="1411">
cent.</word>
<word bottom="1385" left="1454" right="1548" top="1417">
Sales</word>
<word bottom="1385" left="1562" right="1599" top="1417">
of</word>
<word bottom="1385" left="1608" right="1670" top="1406">
our</word>
<word bottom="1385" left="1682" right="1920" top="1416">

anthelmintic
</word>
<word bottom="1375" left="1934" right="2052" top="1417">
family</word>
<word bottom="1385" left="2065" right="2102" top="1416">
of</word>
<word bottom="1375" left="2111" right="2271" top="1417">
products</word>
<word bottom="1339" left="1352" right="1426" top="1359">
rose</word>
<word bottom="1329" left="1438" right="1480" top="1371">
by</word>
<word bottom="1340" left="1495" right="1534" top="1367">

13
</word>
<word bottom="1330" left="1549" right="1697" top="1365">
percent,</word>
<word bottom="1339" left="1712" right="1779" top="1371">
and</word>
<word bottom="1340" left="1792" right="1945" top="1369">

Coxistac
</word>
<word bottom="1339" left="1959" right="2046" top="1371">
sales</word>
<word bottom="1339" left="2060" right="2237" top="1371">
increased</word>
<word bottom="1330" left="2248" right="2291" top="1371">
by</word>
<word bottom="1293" left="1353" right="1371" top="1320">

9
</word>
<word bottom="1283" left="1385" right="1532" top="1320">
percent.</word>
<word bottom="1294" left="1547" right="1618" top="1325">
The</word>
<word bottom="1294" left="1632" right="1650" top="1321">

9
</word>
<word bottom="1283" left="1664" right="1802" top="1320">
percent</word>
<word bottom="1294" left="1816" right="1951" top="1325">
decline</word>
<word bottom="1295" left="1965" right="2000" top="1324">
in</word>
<word bottom="1283" left="2014" right="2188" top="1323">
operating</word>
<word bottom="1284" left="2201" right="2300" top="1325">
profit</word>
<word bottom="1247" left="1351" right="1479" top="1279">
reflects</word>
<word bottom="1248" left="1492" right="1549" top="1279">
the</word>
<word bottom="1247" left="1562" right="1673" top="1279">
initial</word>
<word bottom="1238" left="1685" right="1958" top="1279">
manufacturing</word>
<word bottom="1238" left="1972" right="2112" top="1274">
start-up</word>
<word bottom="1238" left="2126" right="2291" top="1268">
expenses</word>
<word bottom="1201" left="1352" right="1401" top="1233">
for</word>
<word bottom="1202" left="1414" right="1537" top="1233">
several</word>
<word bottom="1202" left="1550" right="1627" top="1223">
new</word>
<word bottom="1191" left="1639" right="1799" top="1233">
products</word>
<word bottom="1202" left="1813" right="1848" top="1222">
as</word>
<word bottom="1202" left="1861" right="1938" top="1233">
well</word>
<word bottom="1202" left="1952" right="1987" top="1223">
as</word>
<word bottom="1192" left="2000" right="2108" top="1234">
heavy</word>
<word bottom="1192" left="2121" right="2282" top="1233">
expendi-</word>
<word bottom="1155" left="1351" right="1441" top="1182">
tures</word>
<word bottom="1156" left="1454" right="1486" top="1182">
to</word>
<word bottom="1146" left="1501" right="1644" top="1183">
support</word>
<word bottom="1155" left="1656" right="1732" top="1176">
new</word>
<word bottom="1146" left="1744" right="1889" top="1187">
product</word>
<word bottom="1155" left="1902" right="2162" top="1188">
introductions.</word>
<word bottom="377" left="1825" right="1999" top="405">

Dectomax,
</word>
<word bottom="380" left="2013" right="2069" top="398">
our</word>
<word bottom="381" left="2077" right="2147" top="398">
new</word>
<word bottom="323" left="1827" right="2040" top="358">

antiparasitic
</word>
<word bottom="323" left="2052" right="2144" top="354">
agent</word>
<word bottom="323" left="2148" right="2200" top="358">
for</word>
<word bottom="279" left="1826" right="1979" top="310">
livestock,</word>
<word bottom="282" left="1991" right="2054" top="306">
met</word>
<word bottom="283" left="2064" right="2135" top="309">
with</word>
<word bottom="283" left="2145" right="2271" top="309">
notable</word>
<word bottom="234" left="1826" right="1948" top="251">
success</word>
<word bottom="235" left="1958" right="1989" top="260">
in</word>
<word bottom="233" left="2000" right="2102" top="260">
Brazil</word>
<word bottom="234" left="2112" right="2142" top="259">
in</word>
<word bottom="234" left="2156" right="2238" top="257">

1993.
</word>
<word bottom="2679" left="1145" right="1260" top="2705">
Annual</word>
<word bottom="2644" left="1108" right="1134" top="2669">

%
</word>
<word bottom="2638" left="1148" right="1259" top="2671">
Change</word>
<word bottom="2590" left="303" right="435" top="2620">
(millions</word>
<word bottom="2587" left="446" right="476" top="2620">
of</word>
<word bottom="2590" left="482" right="594" top="2621">
dollars)</word>
<word bottom="2595" left="708" right="774" top="2616">
1
993
</word>
<word bottom="2595" left="843" right="911" top="2617">

1992
</word>
<word bottom="2595" left="955" right="1020" top="2616">

1991
</word>
<word bottom="2595" left="1066" right="1149" top="2620">

93/92
</word>
<word bottom="2595" left="1178" right="1258" top="2621">

92/91
</word>
<word bottom="2540" left="303" right="377" top="2566">
Sales</word>
<word bottom="2538" left="682" right="774" top="2563">

$578.0
</word>
<word bottom="2539" left="813" right="910" top="2564">

$560.8
</word>
<word bottom="2538" left="926" right="1021" top="2564">

$526.1
</word>
<word bottom="2540" left="1113" right="1179" top="2566">

+3%
</word>
<word bottom="2540" left="1226" right="1291" top="2566">

+7%
</word>
<word bottom="2490" left="302" right="449" top="2523">
Operating</word>
<word bottom="2498" left="459" right="538" top="2524">
Profit</word>
<word bottom="2499" left="717" right="773" top="2520">

37.5
</word>
<word bottom="2499" left="849" right="910" top="2521">

41.2
</word>
<word bottom="2499" left="962" right="1023" top="2520">

42.4
</word>
<word bottom="2499" left="1113" right="1148" top="2521">

—9
</word>
<word bottom="2500" left="1226" right="1259" top="2521">

—3
</word>
</words>
</ocrresult>

